bitonic_sort_pip.v
module bitonic_sort(clk,rst,in1,in2,in3,in4,dir,out1,out2,out3,out4);
input [7:0] in1,in2,in3,in4;
input dir,clk,rst;
output reg [7:0] out1,out2,out3,out4;
wire [7:0] w1 [3:0];

assign w1[0] = (in1 > in2) ? in2 : in1;
assign w1[1] = (in1 > in2) ? in1 : in2;
assign w1[2] = (in3 > in4) ? in3 : in4;
assign w1[3] = (in3 > in4) ? in4 : in3;


reg dir1;
reg [7:0] r1 [3:0];
always @ (posedge clk or posedge rst)
begin
        if (rst)
        begin
            r1[0] <= 0;
            r1[1] <= 0;
            r1[2] <= 0;
            r1[3] <= 0;
            dir1 <= 0;
        end
        else
        begin
            r1[0] <= w1[0];
            r1[1] <= w1[1];
            r1[2] <= w1[2];
            r1[3] <= w1[3];
            dir1 <= dir;
        end
end

wire [7:0] w2 [3:0];
assign w2[0] = (r1[0]  > r1[2]) ? r1[2] : r1[0];
assign w2[2] = (r1[0]  > r1[2]) ? r1[0] : r1[2];
assign w2[1] = (r1[1]  > r1[3]) ? r1[3] : r1[1];
assign w2[3] = (r1[1]  > r1[3]) ? r1[1] : r1[3];

reg [7:0] r2 [3:0];
reg dir2;
always @ (posedge clk or posedge rst)
begin
        if (rst)
        begin
            r2[0] <= 0;
            r2[1] <= 0;
            r2[2] <= 0;
            r2[3] <= 0;
            dir2 <= 0;
        end
        else
        begin
            r2[0] <= w2[0];
            r2[1] <= w2[1];
            r2[2] <= w2[2];
            r2[3] <= w2[3];
            dir2 <= dir1;;
        end
end


wire [7:0] w3 [3:0];
assign w3[0] = (r2[0] > r2 [1]) ? r2[1] : r2[0];
assign w3[1] = (r2[0] > r2 [1]) ? r2[0] : r2[1];
assign w3[2] = (r2[2] > r2 [3]) ? r2[3] : r2[2];
assign w3[3] = (r2[2] > r2 [3]) ? r2[2] : r2[3];

always @ (posedge clk or posedge rst)
begin
    if (rst)
        begin
            out1 <= 0;
            out2 <= 0;
            out3 <= 0;
            out4 <= 0;
        end
    else
        begin
            if (dir2)       //1 for assending and 0 for desending
            begin
                out1 <= w3[0];
                out2 <= w3[1];
                out3 <= w3[2];
                out4 <= w3[3];
            end   
            else
            begin
                out1 <= w3[3];
                out2 <= w3[2];
                out3 <= w3[1];
                out4 <= w3[0];


            end        

        end

end



endmodule

SHEAR_SORTING for MEDIAN FILTERING/4x4_SORTER(Kernel)/shear_sort_pipelined/using_bitonic sort/bitonic_sorters/bitonic_sort_pip_tb.v
`timescale 1ns/1ps

module bitonic_sort_tb;

    // 1. Signals
    reg clk;
    reg rst;
    reg [7:0] in1, in2, in3, in4;
    reg dir;
    wire [7:0] out1, out2, out3, out4;

    // 2. Instantiate the Unit Under Test (UUT)
    bitonic_sort uut (
        .clk(clk), .rst(rst),
        .in1(in1), .in2(in2), .in3(in3), .in4(in4),
        .dir(dir),
        .out1(out1), .out2(out2), .out3(out3), .out4(out4)
    );

    // 3. Clock Generation (100MHz)
    always #5 clk = ~clk;

    // 4. Stimulus
    initial begin
        // Initialize
        clk = 0;
        rst = 1;
        in1 = 0; in2 = 0; in3 = 0; in4 = 0;
        dir = 0;

        // Reset Pulse
        #20 rst = 0;

        // --- Test Case 1: Ascending Sort (dir = 1) ---
        @(posedge clk);
        in1 = 8'd15; in2 = 8'd2; in3 = 8'd9; in4 = 8'd1;
        dir = 1;
        
        $display("Time %0t: Inputs provided [%d, %d, %d, %d]", $time, in1, in2, in3, in4);

        // Wait for Pipeline Latency (3 Cycles)
        repeat(3) @(posedge clk);
        
        // At the 4th posedge after input, the output is ready
        #1; // Small delay to let logic settle
        $display("Time %0t: Output (Asc)  [%d, %d, %d, %d]", $time, out1, out2, out3, out4);

        // --- Test Case 2: Descending Sort (dir = 0) ---
        @(posedge clk);
        in1 = 8'd5; in2 = 8'd12; in3 = 8'd3; in4 = 8'd8;
        dir = 0;

        $display("Time %0t: Inputs provided [%d, %d, %d, %d]", $time, in1, in2, in3, in4);

        repeat(3) @(posedge clk);
        #1;
        $display("Time %0t: Output (Desc) [%d, %d, %d, %d]", $time, out1, out2, out3, out4);

        #50 $finish;
    end

    // 5. Waveform Dump
    initial begin
        $dumpfile("bitonic_sort.vcd");
        $dumpvars(0, bitonic_sort_tb);
    end

endmodule

bitonic_sort.vcd
$date
	Thu Jan 15 02:37:07 2026
$end
$version
	Icarus Verilog
$end
$timescale
	1ps
$end
$scope module bitonic_sort_tb $end
$var wire 8 ! out4 [7:0] $end
$var wire 8 " out3 [7:0] $end
$var wire 8 # out2 [7:0] $end
$var wire 8 $ out1 [7:0] $end
$var reg 1 % clk $end
$var reg 1 & dir $end
$var reg 8 ' in1 [7:0] $end
$var reg 8 ( in2 [7:0] $end
$var reg 8 ) in3 [7:0] $end
$var reg 8 * in4 [7:0] $end
$var reg 1 + rst $end
$scope module uut $end
$var wire 1 % clk $end
$var wire 1 & dir $end
$var wire 8 , in1 [7:0] $end
$var wire 8 - in2 [7:0] $end
$var wire 8 . in3 [7:0] $end
$var wire 8 / in4 [7:0] $end
$var wire 1 + rst $end
$var reg 1 0 dir1 $end
$var reg 1 1 dir2 $end
$var reg 8 2 out1 [7:0] $end
$var reg 8 3 out2 [7:0] $end
$var reg 8 4 out3 [7:0] $end
$var reg 8 5 out4 [7:0] $end
$upscope $end
$upscope $end
$enddefinitions $end
$comment Show the parameter values. $end
$dumpall
$end
#0
$dumpvars
b0 5
b0 4
b0 3
b0 2
01
00
b0 /
b0 .
b0 -
b0 ,
1+
b0 *
b0 )
b0 (
b0 '
0&
0%
b0 $
b0 #
b0 "
b0 !
$end
#5000
1%
#10000
0%
#15000
1%
#20000
0%
0+
#25000
10
1&
b1 *
b1 /
b1001 )
b1001 .
b10 (
b10 -
b1111 '
b1111 ,
1%
#30000
0%
#35000
11
1%
#40000
0%
#45000
1%
#50000
0%
#55000
b1111 !
b1111 5
b1001 "
b1001 4
b10 #
b10 3
b1 $
b1 2
1%
#60000
0%
#65000
00
0&
b1000 *
b1000 /
b11 )
b11 .
b1100 (
b1100 -
b101 '
b101 ,
1%
#70000
0%
#75000
01
1%
#80000
0%
#85000
b1 !
b1 5
b10 "
b10 4
b1001 #
b1001 3
b1111 $
b1111 2
1%
#90000
0%
#95000
b11 !
b11 5
b101 "
b101 4
b1000 #
b1000 3
b1100 $
b1100 2
1%
