SHEAR_SORTING for MEDIAN FILTERING/4x4_SORTER(Kernel)/shear_sort_pipelined/using_bitonic sort/bitonic_sorters/bitonic_sort.v
module bitonic_sort(in1,in2,in3,in4,dir,out1,out2,out3,out4);
input [7:0] in1,in2,in3,in4;
input dir;
output  [7:0] out1,out2,out3,out4;
wire [7:0] w1 [3:0];

assign w1[0] = (in1 > in2) ? in2 : in1;
assign w1[1] = (in1 > in2) ? in1 : in2;
assign w1[2] = (in3 > in4) ? in3 : in4;
assign w1[3] = (in3 > in4) ? in4 : in3;


wire [7:0] w2 [3:0];
assign w2[0] = (w1[0]  > w1[2]) ? w1[2] : w1[0];
assign w2[2] = (w1[0]  > w1[2]) ? w1[0] : w1[2];
assign w2[1] = (w1[1]  > w1[3]) ? w1[3] : w1[1];
assign w2[3] = (w1[1]  > w1[3]) ? w1[1] : w1[3];


wire [7:0] w3 [3:0];
assign w3[0] = (w2[0] > w2 [1]) ? w2[1] : w2[0];
assign w3[1] = (w2[0] > w2 [1]) ? w2[0] : w2[1];
assign w3[2] = (w2[2] > w2 [3]) ? w2[3] : w2[2];
assign w3[3] = (w2[2] > w2 [3]) ? w2[2] : w2[3];

assign out1 = dir ? w3[0] : w3[3];
assign out2 = dir ? w3[1] : w3[2];
assign out3 = dir ? w3[2] : w3[1];
assign out4 = dir ? w3[3] : w3[0];


endmodule

shear_sort_pip_fsm_bitonic.v
`include "bitonic_sort.v"


module shear_sort_pip_fsm_bitonic(clk,rst,start,in_1,in_2,in_3,in_4,in_5,in_6,in_7,in_8,in_9,in_10,in_11,in_12,in_13,in_14,in_15,in_16,
out_1,out_2,out_3,out_4,out_5,out_6,out_7,out_8,out_9,out_10,out_11,out_12,out_13,out_14,out_15,out_16,done);

input clk,rst,start;
input [7:0]in_1,in_2,in_3,in_4,in_5,in_6,in_7,in_8,in_9,in_10,in_11,in_12,in_13,in_14,in_15,in_16;
output [7:0]out_1,out_2,out_3,out_4,out_5,out_6,out_7,out_8,out_9,out_10,out_11,out_12,out_13,out_14,out_15,out_16;
output reg done;

reg [1:0] iter_counter;

reg [1:0]state;
localparam  IDLE = 2'b00;
localparam  LOAD = 2'b01;
localparam  SORTER = 2'b10;
localparam  DONE = 2'b11;

reg [7:0] in_mat [15:0] ;
wire [7:0] rw [15:0];
wire [7:0] cl [15:0];


bitonic_sort r0 (in_mat[0],in_mat[1],in_mat[2],in_mat[3],1'b1,rw[0],rw[1],rw[2],rw[3]);
bitonic_sort r1 (in_mat[4],in_mat[5],in_mat[6],in_mat[7],1'b0,rw[4],rw[5],rw[6],rw[7]);
bitonic_sort r2 (in_mat[8],in_mat[9],in_mat[10],in_mat[11],1'b1,rw[8],rw[9],rw[10],rw[11]);
bitonic_sort r3 (in_mat[12],in_mat[13],in_mat[14],in_mat[15],1'b0,rw[12],rw[13],rw[14],rw[15]);

bitonic_sort c0 (rw[0],  rw[4],  rw[8],  rw[12],1'b1,
                cl[0],  cl[4],  cl[8],  cl[12]);

bitonic_sort c1 (rw[1],  rw[5],  rw[9],  rw[13],1'b1,
                cl[1],  cl[5],  cl[9],  cl[13]);

bitonic_sort c2 (rw[2],  rw[6],  rw[10], rw[14],1'b1,
                cl[2],  cl[6],  cl[10], cl[14]);
bitonic_sort c3 (rw[3],  rw[7],  rw[11], rw[15],1'b1,
                cl[3],  cl[7],  cl[11], cl[15]);

always @ (posedge clk or posedge rst)
begin
    if (rst)
    begin
        state <= IDLE;
        iter_counter <= 0;
        done <= 0;
    end
    else
    begin
        case (state)

        IDLE : begin
                    done <= 0;
                    iter_counter <= 0;
                    if (start) state <= LOAD; 
              end

        LOAD : begin
                    in_mat[0] <= in_1; in_mat[1] <= in_2; in_mat[2] <= in_3; in_mat[3] <= in_4;
                    in_mat[4] <= in_5; in_mat[5] <= in_6; in_mat[6] <= in_7; in_mat[7] <= in_8;
                    in_mat[8] <= in_9; in_mat[9] <= in_10; in_mat[10] <= in_11; in_mat[11] <= in_12;
                    in_mat[12] <= in_13; in_mat[13] <= in_14; in_mat[14] <= in_15; in_mat[15] <= in_16;
                    state <= SORTER;
               end

        SORTER : begin
                in_mat[0] <= cl[0]; in_mat[1] <= cl[1]; in_mat[2] <= cl[2]; in_mat[3] <= cl[3];
                in_mat[4] <= cl[4]; in_mat[5] <= cl[5]; in_mat[6] <= cl[6]; in_mat[7] <= cl[7];
                in_mat[8] <= cl[8]; in_mat[9] <= cl[9]; in_mat[10] <= cl[10]; in_mat[11] <= cl[11];
                in_mat[12] <= cl[12]; in_mat[13] <= cl[13]; in_mat[14] <= cl[14]; in_mat[15] <= cl[15];

                if (iter_counter == 2) state <= DONE;
                else begin 
                    iter_counter <= iter_counter + 1;
                     end
                end

        DONE: begin
            done <= 1;
            if (!start) state <= IDLE;

        end

        endcase
        
        
    
    
    end

end

assign out_1 = in_mat[0]; 
assign out_2 = in_mat[1]; 
assign out_3 = in_mat[2]; 
assign out_4 = in_mat[3]; 
assign out_5 = in_mat[4]; 
assign out_6 = in_mat[5]; 
assign out_7 = in_mat[6]; 
assign out_8 = in_mat[7]; 
assign out_9 = in_mat[8]; 
assign out_10 = in_mat[9]; 
assign out_11 = in_mat[10]; 
assign out_12 = in_mat[11]; 
assign out_13 = in_mat[12]; 
assign out_14 = in_mat[13]; 
assign out_15 = in_mat[14]; 
assign out_16 = in_mat[15]; 



















endmodule

SHEAR_SORTING for MEDIAN FILTERING/4x4_SORTER(Kernel)/shear_sort_pipelined/using_bitonic sort/shear_sort_using_bitonic sort/shear_sort_pip_fsm_tb_bitonic.v
`include "shear_sort_pip_fsm_bitonic.v"
`timescale 1ns/1ps

module shear_sort_pip_fsm_tb_bitonic;

    // 1. Signals
    reg clk;
    reg rst;
    reg start;
    
    // Inputs
    reg [7:0] in_1,  in_2,  in_3,  in_4,  in_5,  in_6,  in_7,  in_8;
    reg [7:0] in_9,  in_10, in_11, in_12, in_13, in_14, in_15, in_16;
    
    // Outputs
    wire [7:0] out_1,  out_2,  out_3,  out_4,  out_5,  out_6,  out_7,  out_8;
    wire [7:0] out_9,  out_10, out_11, out_12, out_13, out_14, out_15, out_16;
    wire done;



    // 2. Instantiate the Design Under Test (DUT)
    shear_sort_pip_fsm_bitonic dut (
        .clk(clk), .rst(rst), .start(start),
        .in_1(in_1),   .in_2(in_2),   .in_3(in_3),   .in_4(in_4),
        .in_5(in_5),   .in_6(in_6),   .in_7(in_7),   .in_8(in_8),
        .in_9(in_9),   .in_10(in_10), .in_11(in_11), .in_12(in_12),
        .in_13(in_13), .in_14(in_14), .in_15(in_15), .in_16(in_16),
        .out_1(out_1),   .out_2(out_2),   .out_3(out_3),   .out_4(out_4),
        .out_5(out_5),   .out_6(out_6),   .out_7(out_7),   .out_8(out_8),
        .out_9(out_9),   .out_10(out_10), .out_11(out_11), .out_12(out_12),
        .out_13(out_13), .out_14(out_14), .out_15(out_15), .out_16(out_16),
        .done(done)
    );

    // 3. Clock Generation (100MHz)
    always #5 clk = (clk === 1'b0); // Initializes to 0 automatically

    // 4. Monitoring (Prints every state change)
    initial begin
        $monitor("Time: %0t | State: %b | Count: %d | Done: %b", $time, dut.state, dut.iter_counter, done);
    end

    // 5. Stimulus
    initial begin
        // Initialize
        clk = 0;
        rst = 1;      // Start in Reset (Active High)
        start = 0;
        
        // Unsorted input data
        in_1=10;  in_2=2;   in_3=5;   in_4=1;
        in_5=15;  in_6=8;   in_7=12;  in_8=4;
        in_9=3;   in_10=11; in_11=6;  in_12=9;
        in_13=14; in_14=0;  in_15=7;  in_16=13;

        // Sequence
        #20 rst = 0;             // Release Reset
        @(posedge clk);
        start = 1;
        @(posedge clk);
        start = 0; // The FSM must see start go to 0 to stay in the loop!       // Trigger Start
             // Clear Start

        // Wait for Hardware to finish 3 iterations
        wait(done == 1'b1);
        #1; // Wait 1ns for assignments to settle

        // 6. Display Output Matrix
        $display("\n========================================");
        $display("   SHEAR SORT FINAL OUTPUT MATRIX");
        $display("========================================");
        $display("Row 0: %d\t%d\t%d\t%d", out_1,  out_2,  out_3,  out_4);
        $display("Row 1: %d\t%d\t%d\t%d", out_5,  out_6,  out_7,  out_8);
        $display("Row 2: %d\t%d\t%d\t%d", out_9,  out_10, out_11, out_12);
        $display("Row 3: %d\t%d\t%d\t%d", out_13, out_14, out_15, out_16);
        $display("========================================\n");
        
        $finish;
    end

    // 7. Waveform Dump
    initial begin
        $dumpfile("shear_sort_fsm_bit.vcd");
        $dumpvars(0, shear_sort_pip_fsm_tb_bitonic);
    end

endmodule

shear_sort_fsm_bit.vcd
$date
	Fri Jan 16 12:07:48 2026
$end
$version
	Icarus Verilog
$end
$timescale
	1ps
$end
$scope module shear_sort_pip_fsm_tb_bitonic $end
$var wire 8 ! out_9 [7:0] $end
$var wire 8 " out_8 [7:0] $end
$var wire 8 # out_7 [7:0] $end
$var wire 8 $ out_6 [7:0] $end
$var wire 8 % out_5 [7:0] $end
$var wire 8 & out_4 [7:0] $end
$var wire 8 ' out_3 [7:0] $end
$var wire 8 ( out_2 [7:0] $end
$var wire 8 ) out_16 [7:0] $end
$var wire 8 * out_15 [7:0] $end
$var wire 8 + out_14 [7:0] $end
$var wire 8 , out_13 [7:0] $end
$var wire 8 - out_12 [7:0] $end
$var wire 8 . out_11 [7:0] $end
$var wire 8 / out_10 [7:0] $end
$var wire 8 0 out_1 [7:0] $end
$var wire 1 1 done $end
$var reg 1 2 clk $end
$var reg 8 3 in_1 [7:0] $end
$var reg 8 4 in_10 [7:0] $end
$var reg 8 5 in_11 [7:0] $end
$var reg 8 6 in_12 [7:0] $end
$var reg 8 7 in_13 [7:0] $end
$var reg 8 8 in_14 [7:0] $end
$var reg 8 9 in_15 [7:0] $end
$var reg 8 : in_16 [7:0] $end
$var reg 8 ; in_2 [7:0] $end
$var reg 8 < in_3 [7:0] $end
$var reg 8 = in_4 [7:0] $end
$var reg 8 > in_5 [7:0] $end
$var reg 8 ? in_6 [7:0] $end
$var reg 8 @ in_7 [7:0] $end
$var reg 8 A in_8 [7:0] $end
$var reg 8 B in_9 [7:0] $end
$var reg 1 C rst $end
$var reg 1 D start $end
$scope module dut $end
$var wire 1 2 clk $end
$var wire 8 E in_1 [7:0] $end
$var wire 8 F in_10 [7:0] $end
$var wire 8 G in_11 [7:0] $end
$var wire 8 H in_12 [7:0] $end
$var wire 8 I in_13 [7:0] $end
$var wire 8 J in_14 [7:0] $end
$var wire 8 K in_15 [7:0] $end
$var wire 8 L in_16 [7:0] $end
$var wire 8 M in_2 [7:0] $end
$var wire 8 N in_3 [7:0] $end
$var wire 8 O in_4 [7:0] $end
$var wire 8 P in_5 [7:0] $end
$var wire 8 Q in_6 [7:0] $end
$var wire 8 R in_7 [7:0] $end
$var wire 8 S in_8 [7:0] $end
$var wire 8 T in_9 [7:0] $end
$var wire 8 U out_1 [7:0] $end
$var wire 8 V out_10 [7:0] $end
$var wire 8 W out_11 [7:0] $end
$var wire 8 X out_12 [7:0] $end
$var wire 8 Y out_13 [7:0] $end
$var wire 8 Z out_14 [7:0] $end
$var wire 8 [ out_15 [7:0] $end
$var wire 8 \ out_16 [7:0] $end
$var wire 8 ] out_2 [7:0] $end
$var wire 8 ^ out_3 [7:0] $end
$var wire 8 _ out_4 [7:0] $end
$var wire 8 ` out_5 [7:0] $end
$var wire 8 a out_6 [7:0] $end
$var wire 8 b out_7 [7:0] $end
$var wire 8 c out_8 [7:0] $end
$var wire 8 d out_9 [7:0] $end
$var wire 1 C rst $end
$var wire 1 D start $end
$var parameter 2 e DONE $end
$var parameter 2 f IDLE $end
$var parameter 2 g LOAD $end
$var parameter 2 h SORTER $end
$var reg 1 1 done $end
$var reg 2 i iter_counter [1:0] $end
$var reg 2 j state [1:0] $end
$scope module c0 $end
$var wire 1 k dir $end
$var wire 8 l out1 [7:0] $end
$var wire 8 m out2 [7:0] $end
$var wire 8 n out3 [7:0] $end
$var wire 8 o out4 [7:0] $end
$var wire 8 p in4 [7:0] $end
$var wire 8 q in3 [7:0] $end
$var wire 8 r in2 [7:0] $end
$var wire 8 s in1 [7:0] $end
$upscope $end
$scope module c1 $end
$var wire 1 t dir $end
$var wire 8 u out1 [7:0] $end
$var wire 8 v out2 [7:0] $end
$var wire 8 w out3 [7:0] $end
$var wire 8 x out4 [7:0] $end
$var wire 8 y in4 [7:0] $end
$var wire 8 z in3 [7:0] $end
$var wire 8 { in2 [7:0] $end
$var wire 8 | in1 [7:0] $end
$upscope $end
$scope module c2 $end
$var wire 1 } dir $end
$var wire 8 ~ out1 [7:0] $end
$var wire 8 !" out2 [7:0] $end
$var wire 8 "" out3 [7:0] $end
$var wire 8 #" out4 [7:0] $end
$var wire 8 $" in4 [7:0] $end
$var wire 8 %" in3 [7:0] $end
$var wire 8 &" in2 [7:0] $end
$var wire 8 '" in1 [7:0] $end
$upscope $end
$scope module c3 $end
$var wire 1 (" dir $end
$var wire 8 )" out1 [7:0] $end
$var wire 8 *" out2 [7:0] $end
$var wire 8 +" out3 [7:0] $end
$var wire 8 ," out4 [7:0] $end
$var wire 8 -" in4 [7:0] $end
$var wire 8 ." in3 [7:0] $end
$var wire 8 /" in2 [7:0] $end
$var wire 8 0" in1 [7:0] $end
$upscope $end
$scope module r0 $end
$var wire 1 1" dir $end
$var wire 8 2" in1 [7:0] $end
$var wire 8 3" in2 [7:0] $end
$var wire 8 4" in3 [7:0] $end
$var wire 8 5" in4 [7:0] $end
$var wire 8 6" out1 [7:0] $end
$var wire 8 7" out2 [7:0] $end
$var wire 8 8" out3 [7:0] $end
$var wire 8 9" out4 [7:0] $end
$upscope $end
$scope module r1 $end
$var wire 1 :" dir $end
$var wire 8 ;" in1 [7:0] $end
$var wire 8 <" in2 [7:0] $end
$var wire 8 =" in3 [7:0] $end
$var wire 8 >" in4 [7:0] $end
$var wire 8 ?" out1 [7:0] $end
$var wire 8 @" out2 [7:0] $end
$var wire 8 A" out3 [7:0] $end
$var wire 8 B" out4 [7:0] $end
$upscope $end
$scope module r2 $end
$var wire 1 C" dir $end
$var wire 8 D" in1 [7:0] $end
$var wire 8 E" in2 [7:0] $end
$var wire 8 F" in3 [7:0] $end
$var wire 8 G" in4 [7:0] $end
$var wire 8 H" out1 [7:0] $end
$var wire 8 I" out2 [7:0] $end
$var wire 8 J" out3 [7:0] $end
$var wire 8 K" out4 [7:0] $end
$upscope $end
$scope module r3 $end
$var wire 1 L" dir $end
$var wire 8 M" in1 [7:0] $end
$var wire 8 N" in2 [7:0] $end
$var wire 8 O" in3 [7:0] $end
$var wire 8 P" in4 [7:0] $end
$var wire 8 Q" out1 [7:0] $end
$var wire 8 R" out2 [7:0] $end
$var wire 8 S" out3 [7:0] $end
$var wire 8 T" out4 [7:0] $end
$upscope $end
$upscope $end
$upscope $end
$enddefinitions $end
$comment Show the parameter values. $end
$dumpall
b10 h
b1 g
b0 f
b11 e
$end
#0
$dumpvars
bx T"
bx S"
bx R"
bx Q"
bx P"
bx O"
bx N"
bx M"
0L"
bx K"
bx J"
bx I"
bx H"
bx G"
bx F"
bx E"
bx D"
1C"
bx B"
bx A"
bx @"
bx ?"
bx >"
bx ="
bx <"
bx ;"
0:"
bx 9"
bx 8"
bx 7"
bx 6"
bx 5"
bx 4"
bx 3"
bx 2"
11"
bx 0"
bx /"
bx ."
bx -"
bx ,"
bx +"
bx *"
bx )"
1("
bx '"
bx &"
bx %"
bx $"
bx #"
bx ""
bx !"
bx ~
1}
bx |
bx {
bx z
bx y
bx x
bx w
bx v
bx u
1t
bx s
bx r
bx q
bx p
bx o
bx n
bx m
bx l
1k
b0 j
b0 i
bx d
bx c
bx b
bx a
bx `
bx _
bx ^
bx ]
bx \
bx [
bx Z
bx Y
bx X
bx W
bx V
bx U
b11 T
b100 S
b1100 R
b1000 Q
b1111 P
b1 O
b101 N
b10 M
b1101 L
b111 K
b0 J
b1110 I
b1001 H
b110 G
b1011 F
b1010 E
0D
1C
b11 B
b100 A
b1100 @
b1000 ?
b1111 >
b1 =
b101 <
b10 ;
b1101 :
b111 9
b0 8
b1110 7
b1001 6
b110 5
b1011 4
b1010 3
02
01
bx 0
bx /
bx .
bx -
bx ,
bx +
bx *
bx )
bx (
bx '
bx &
bx %
bx $
bx #
bx "
bx !
$end
#5000
12
#10000
02
#15000
12
#20000
02
0C
#25000
b1 j
1D
12
#30000
02
#35000
b1 l
b11 m
b1110 n
b1111 o
b10 u
b110 v
b1100 w
b1101 x
b101 ~
b111 !"
b1000 ""
b1001 #"
b0 )"
b100 *"
b1010 +"
b1011 ,"
b0 -"
b0 T"
b111 $"
b111 S"
b1101 y
b1101 R"
b1110 p
b1110 Q"
b11 q
b11 H"
b110 z
b110 I"
b1001 %"
b1001 J"
b1011 ."
b1011 K"
b100 /"
b100 B"
b1000 &"
b1000 A"
b1100 {
b1100 @"
b1111 r
b1111 ?"
b1 s
b1 6"
b10 |
b10 7"
b101 '"
b101 8"
b1010 0"
b1010 9"
b10 j
b1101 )
b1101 \
b1101 P"
b111 *
b111 [
b111 O"
b0 +
b0 Z
b0 N"
b1110 ,
b1110 Y
b1110 M"
b1001 -
b1001 X
b1001 G"
b110 .
b110 W
b110 F"
b1011 /
b1011 V
b1011 E"
b11 !
b11 d
b11 D"
b100 "
b100 c
b100 >"
b1100 #
b1100 b
b1100 ="
b1000 $
b1000 a
b1000 <"
b1111 %
b1111 `
b1111 ;"
b1 &
b1 _
b1 5"
b101 '
b101 ^
b101 4"
b10 (
b10 ]
b10 3"
b1010 0
b1010 U
b1010 2"
0D
12
#40000
02
#45000
b11 )"
b111 m
b1110 ,"
b101 *"
b100 !"
b1011 ""
b1100 #"
b1010 w
b1000 n
b0 l
b1 u
b10 ~
b1001 +"
b1001 -"
b1001 T"
b1011 $"
b1011 S"
b1111 p
b1111 Q"
b1000 q
b1000 H"
b1010 z
b1010 I"
b1100 %"
b1100 J"
b1110 ."
b1110 K"
b11 /"
b11 B"
b100 &"
b100 A"
b110 {
b110 @"
b111 r
b111 ?"
b0 s
b0 6"
b1 |
b1 7"
b10 '"
b10 8"
b101 0"
b101 9"
b1 i
b1011 )
b1011 \
b1011 P"
b1001 *
b1001 [
b1001 O"
b1101 +
b1101 Z
b1101 N"
b1111 ,
b1111 Y
b1111 M"
b1010 -
b1010 X
b1010 G"
b1000 .
b1000 W
b1000 F"
b1100 /
b1100 V
b1100 E"
b1110 !
b1110 d
b1110 D"
b111 #
b111 b
b111 ="
b110 $
b110 a
b110 <"
b11 %
b11 `
b11 ;"
b0 &
b0 _
b0 5"
b1 0
b1 U
b1 2"
12
#50000
02
#55000
b1110 x
b1011 +"
b1001 w
b1010 ""
b1101 #"
b1100 ,"
b101 !"
b100 *"
b1110 y
b1110 R"
b1100 -"
b1100 T"
b1101 $"
b1101 S"
b1001 z
b1001 I"
b1010 %"
b1010 J"
b1011 ."
b1011 K"
b100 /"
b100 B"
b101 &"
b101 A"
b11 0"
b11 9"
b10 i
b1110 )
b1110 \
b1110 P"
b1100 *
b1100 [
b1100 O"
b1001 -
b1001 X
b1001 G"
b1011 .
b1011 W
b1011 F"
b1010 /
b1010 V
b1010 E"
b1000 !
b1000 d
b1000 D"
b101 "
b101 c
b101 >"
b100 #
b100 b
b100 ="
b111 %
b111 `
b111 ;"
b11 &
b11 _
b11 5"
b10 '
b10 ^
b10 4"
b1 (
b1 ]
b1 3"
b0 0
b0 U
b0 2"
12
#60000
02
#65000
b11 j
b1100 )
b1100 \
b1100 P"
b1101 *
b1101 [
b1101 O"
b1110 +
b1110 Z
b1110 N"
b1011 -
b1011 X
b1011 G"
b1010 .
b1010 W
b1010 F"
b1001 /
b1001 V
b1001 E"
b100 "
b100 c
b100 >"
b101 #
b101 b
b101 ="
12
#70000
02
#75000
b0 j
11
12
