SHEAR_SORTING for MEDIAN FILTERING/4x4_SORTER(Kernel)/shear_sort_pipelined/using normal row and column sort/column_sort.v
module column_sort(in_0,in_1,in_2,in_3,out0,out1,out2,out3);
input [7:0] in_0,in_1,in_2,in_3;

output [7:0]out0,out1,out2,out3;

//intermediate wires
wire [7:0] s_0,s_1,s_2,s_3;
wire [7:0] s1_0,s1_1,s1_2,s1_3;
wire [7:0] s2_0,s2_1,s2_2,s2_3;

        //stage 0
       

      assign  s_0 = (in_0 > in_1) ? in_1 : in_0;
      assign s_1 = (in_0 > in_1) ? in_0 : in_1;
        assign s_2 = (in_2 > in_3) ? in_3 : in_2;
        assign s_3 = (in_2 > in_3) ? in_2 : in_3;

        //stage 1
       

       assign  s1_0 = (s_0 > s_2) ? s_2 : s_0;
       assign  s1_1 = (s_0 > s_2) ? s_0 : s_2;
       assign  s1_2 = (s_1 > s_3) ? s_3 : s_1;
       assign  s1_3 = (s_1 > s_3) ? s_1 : s_3;

        //stage 2

     

       assign  s2_0 = s1_0;
       assign  s2_1 = (s1_1 > s1_2) ? s1_2 : s1_1;
       assign  s2_2 = (s1_1 > s1_2) ? s1_1 : s1_2;
        assign s2_3 = s1_3;

        //sorted 
      assign   out0 = s2_0;
       assign  out1 = s2_1;
       assign  out2 = s2_2;
       assign  out3 = s2_3;

   





endmodule

SHEAR_SORTING for MEDIAN FILTERING/4x4_SORTER(Kernel)/shear_sort_comb/row_sort.v
module row_sort(in_0,in_1,in_2,in_3,out0,out1,out2,out3);
input [7:0] in_0,in_1,in_2,in_3;

output [7:0]out0,out1,out2,out3;

//intermediate wires
wire [7:0] s_0,s_1,s_2,s_3;
wire [7:0] s1_0,s1_1,s1_2,s1_3;
wire [7:0] s2_0,s2_1,s2_2,s2_3;

//stage 0
       

      assign   s_0 = (in_0 > in_1) ? in_1 : in_0;
        assign s_1 = (in_0 > in_1) ? in_0 : in_1;
       assign  s_2 = (in_2 > in_3) ? in_3 : in_2;
      assign   s_3 = (in_2 > in_3) ? in_2 : in_3;

        //stage 1
       

      assign   s1_0 = (s_0 > s_2) ? s_2 : s_0;
      assign   s1_1 = (s_0 > s_2) ? s_0 : s_2;
      assign s1_2 = (s_1 > s_3) ? s_3 : s_1;
      assign   s1_3 = (s_1 > s_3) ? s_1 : s_3;

        //stage 2

     

      assign   s2_0 = s1_0;
       assign  s2_1 = (s1_1 > s1_2) ? s1_2 : s1_1;
       assign  s2_2 = (s1_1 > s1_2) ? s1_1 : s1_2;
      assign   s2_3 = s1_3;

        //sorted 
       assign  out0 = s2_0;
        assign  out1 = s2_1;
       assign  out2 = s2_2;
       assign  out3 = s2_3;

    




endmodule

shear_sort_pip_fsm.v
`include "row_sort.v"
`include "column_sort.v"


module shear_sort_pip_fsm(clk,rst,start,in_1,in_2,in_3,in_4,in_5,in_6,in_7,in_8,in_9,in_10,in_11,in_12,in_13,in_14,in_15,in_16,
out_1,out_2,out_3,out_4,out_5,out_6,out_7,out_8,out_9,out_10,out_11,out_12,out_13,out_14,out_15,out_16,done);

input clk,rst,start;
input [7:0]in_1,in_2,in_3,in_4,in_5,in_6,in_7,in_8,in_9,in_10,in_11,in_12,in_13,in_14,in_15,in_16;
output [7:0]out_1,out_2,out_3,out_4,out_5,out_6,out_7,out_8,out_9,out_10,out_11,out_12,out_13,out_14,out_15,out_16;
output reg done;

reg [1:0] iter_counter;

reg [1:0]state;
localparam  IDLE = 2'b00;
localparam  LOAD = 2'b01;
localparam  SORTER = 2'b10;
localparam  DONE = 2'b11;

reg [7:0] in_mat [15:0] ;
wire [7:0] rw [15:0];
wire [7:0] cl [15:0];


row_sort r0 (in_mat[0],in_mat[1],in_mat[2],in_mat[3],rw[0],rw[1],rw[2],rw[3]);
row_sort r1 (in_mat[4],in_mat[5],in_mat[6],in_mat[7],rw[7],rw[6],rw[5],rw[4]);
row_sort r2 (in_mat[8],in_mat[9],in_mat[10],in_mat[11],rw[8],rw[9],rw[10],rw[11]);
row_sort r3 (in_mat[12],in_mat[13],in_mat[14],in_mat[15],rw[15],rw[14],rw[13],rw[12]);

column_sort c0 (rw[0],  rw[4],  rw[8],  rw[12],
                cl[0],  cl[4],  cl[8],  cl[12]);

column_sort c1 (rw[1],  rw[5],  rw[9],  rw[13],
                cl[1],  cl[5],  cl[9],  cl[13]);

column_sort c2 (rw[2],  rw[6],  rw[10], rw[14],
                cl[2],  cl[6],  cl[10], cl[14]);
column_sort c3 (rw[3],  rw[7],  rw[11], rw[15],
                cl[3],  cl[7],  cl[11], cl[15]);

always @ (posedge clk or posedge rst)
begin
    if (rst)
    begin
        state <= IDLE;
        iter_counter <= 0;
        done <= 0;
    end
    else
    begin
        case (state)

        IDLE : begin
                    done <= 0;
                    iter_counter <= 0;
                    if (start) state <= LOAD; 
              end

        LOAD : begin
                    in_mat[0] <= in_1; in_mat[1] <= in_2; in_mat[2] <= in_3; in_mat[3] <= in_4;
                    in_mat[4] <= in_5; in_mat[5] <= in_6; in_mat[6] <= in_7; in_mat[7] <= in_8;
                    in_mat[8] <= in_9; in_mat[9] <= in_10; in_mat[10] <= in_11; in_mat[11] <= in_12;
                    in_mat[12] <= in_13; in_mat[13] <= in_14; in_mat[14] <= in_15; in_mat[15] <= in_16;
                    state <= SORTER;
               end

        SORTER : begin
                in_mat[0] <= cl[0]; in_mat[1] <= cl[1]; in_mat[2] <= cl[2]; in_mat[3] <= cl[3];
                in_mat[4] <= cl[4]; in_mat[5] <= cl[5]; in_mat[6] <= cl[6]; in_mat[7] <= cl[7];
                in_mat[8] <= cl[8]; in_mat[9] <= cl[9]; in_mat[10] <= cl[10]; in_mat[11] <= cl[11];
                in_mat[12] <= cl[12]; in_mat[13] <= cl[13]; in_mat[14] <= cl[14]; in_mat[15] <= cl[15];

                if (iter_counter == 2) state <= DONE;
                else begin 
                    iter_counter <= iter_counter + 1;
                     end
                end

        DONE: begin
            done <= 1;
            if (!start) state <= IDLE;

        end

        endcase
        
        
    
    
    end

end

assign out_1 = in_mat[0]; 
assign out_2 = in_mat[1]; 
assign out_3 = in_mat[2]; 
assign out_4 = in_mat[3]; 
assign out_5 = in_mat[4]; 
assign out_6 = in_mat[5]; 
assign out_7 = in_mat[6]; 
assign out_8 = in_mat[7]; 
assign out_9 = in_mat[8]; 
assign out_10 = in_mat[9]; 
assign out_11 = in_mat[10]; 
assign out_12 = in_mat[11]; 
assign out_13 = in_mat[12]; 
assign out_14 = in_mat[13]; 
assign out_15 = in_mat[14]; 
assign out_16 = in_mat[15]; 



endmodule

SHEAR_SORTING for MEDIAN FILTERING/4x4_SORTER(Kernel)/shear_sort_pipelined/using normal row and column sort/shear_sort_fsm_pip_tb.v
`include "shear_sort_pip_fsm.v"
`timescale 1ns/1ps

module shear_sort_pip_fsm_tb;

    // 1. Signals
    reg clk;
    reg rst;
    reg start;
    
    // Inputs
    reg [7:0] in_1,  in_2,  in_3,  in_4,  in_5,  in_6,  in_7,  in_8;
    reg [7:0] in_9,  in_10, in_11, in_12, in_13, in_14, in_15, in_16;
    
    // Outputs
    wire [7:0] out_1,  out_2,  out_3,  out_4,  out_5,  out_6,  out_7,  out_8;
    wire [7:0] out_9,  out_10, out_11, out_12, out_13, out_14, out_15, out_16;
    wire done;



    // 2. Instantiate the Design Under Test (DUT)
    shear_sort_pip_fsm dut (
        .clk(clk), .rst(rst), .start(start),
        .in_1(in_1),   .in_2(in_2),   .in_3(in_3),   .in_4(in_4),
        .in_5(in_5),   .in_6(in_6),   .in_7(in_7),   .in_8(in_8),
        .in_9(in_9),   .in_10(in_10), .in_11(in_11), .in_12(in_12),
        .in_13(in_13), .in_14(in_14), .in_15(in_15), .in_16(in_16),
        .out_1(out_1),   .out_2(out_2),   .out_3(out_3),   .out_4(out_4),
        .out_5(out_5),   .out_6(out_6),   .out_7(out_7),   .out_8(out_8),
        .out_9(out_9),   .out_10(out_10), .out_11(out_11), .out_12(out_12),
        .out_13(out_13), .out_14(out_14), .out_15(out_15), .out_16(out_16),
        .done(done)
    );

    // 3. Clock Generation (100MHz)
    always #5 clk = (clk === 1'b0); // Initializes to 0 automatically

    // 4. Monitoring (Prints every state change)
    initial begin
        $monitor("Time: %0t | State: %b | Count: %d | Done: %b", $time, dut.state, dut.iter_counter, done);
    end

    // 5. Stimulus
    initial begin
        // Initialize
        clk = 0;
        rst = 1;      // Start in Reset (Active High)
        start = 0;
        
        // Unsorted input data
        // Case 1: Gradient
in_1=10;  in_2=80;  in_3=30;  in_4=5;
in_5=150; in_6=100; in_7=120; in_8=90;
in_9=200; in_10=180; in_11=220; in_12=160;
in_13=255; in_14=240; in_15=250; in_16=230;

        // Sequence
        #20 rst = 0;             // Release Reset
        @(posedge clk);
        start = 1;
        @(posedge clk);
        start = 0; // The FSM must see start go to 0 to stay in the loop!       // Trigger Start
             // Clear Start

        // Wait for Hardware to finish 3 iterations
        wait(done == 1'b1);
        #1; // Wait 1ns for assignments to settle

        // 6. Display Output Matrix
        $display("\n========================================");
        $display("   SHEAR SORT FINAL OUTPUT MATRIX");
        $display("========================================");
        $display("Row 0: %d\t%d\t%d\t%d", out_1,  out_2,  out_3,  out_4);
        $display("Row 1: %d\t%d\t%d\t%d", out_5,  out_6,  out_7,  out_8);
        $display("Row 2: %d\t%d\t%d\t%d", out_9,  out_10, out_11, out_12);
        $display("Row 3: %d\t%d\t%d\t%d", out_13, out_14, out_15, out_16);
        $display("========================================\n");
        
        $finish;
    end

    // 7. Waveform Dump
    initial begin
        $dumpfile("shear_sort_fsm.vcd");
        $dumpvars(0, shear_sort_pip_fsm_tb);
    end

endmodule

shear_sort_fsm.vcd
$date
	Thu Jan 15 02:52:46 2026
$end
$version
	Icarus Verilog
$end
$timescale
	1ps
$end
$scope module shear_sort_pip_fsm_tb $end
$var wire 8 ! out_9 [7:0] $end
$var wire 8 " out_8 [7:0] $end
$var wire 8 # out_7 [7:0] $end
$var wire 8 $ out_6 [7:0] $end
$var wire 8 % out_5 [7:0] $end
$var wire 8 & out_4 [7:0] $end
$var wire 8 ' out_3 [7:0] $end
$var wire 8 ( out_2 [7:0] $end
$var wire 8 ) out_16 [7:0] $end
$var wire 8 * out_15 [7:0] $end
$var wire 8 + out_14 [7:0] $end
$var wire 8 , out_13 [7:0] $end
$var wire 8 - out_12 [7:0] $end
$var wire 8 . out_11 [7:0] $end
$var wire 8 / out_10 [7:0] $end
$var wire 8 0 out_1 [7:0] $end
$var wire 1 1 done $end
$var reg 1 2 clk $end
$var reg 8 3 in_1 [7:0] $end
$var reg 8 4 in_10 [7:0] $end
$var reg 8 5 in_11 [7:0] $end
$var reg 8 6 in_12 [7:0] $end
$var reg 8 7 in_13 [7:0] $end
$var reg 8 8 in_14 [7:0] $end
$var reg 8 9 in_15 [7:0] $end
$var reg 8 : in_16 [7:0] $end
$var reg 8 ; in_2 [7:0] $end
$var reg 8 < in_3 [7:0] $end
$var reg 8 = in_4 [7:0] $end
$var reg 8 > in_5 [7:0] $end
$var reg 8 ? in_6 [7:0] $end
$var reg 8 @ in_7 [7:0] $end
$var reg 8 A in_8 [7:0] $end
$var reg 8 B in_9 [7:0] $end
$var reg 1 C rst $end
$var reg 1 D start $end
$scope module dut $end
$var wire 1 2 clk $end
$var wire 8 E in_1 [7:0] $end
$var wire 8 F in_10 [7:0] $end
$var wire 8 G in_11 [7:0] $end
$var wire 8 H in_12 [7:0] $end
$var wire 8 I in_13 [7:0] $end
$var wire 8 J in_14 [7:0] $end
$var wire 8 K in_15 [7:0] $end
$var wire 8 L in_16 [7:0] $end
$var wire 8 M in_2 [7:0] $end
$var wire 8 N in_3 [7:0] $end
$var wire 8 O in_4 [7:0] $end
$var wire 8 P in_5 [7:0] $end
$var wire 8 Q in_6 [7:0] $end
$var wire 8 R in_7 [7:0] $end
$var wire 8 S in_8 [7:0] $end
$var wire 8 T in_9 [7:0] $end
$var wire 8 U out_1 [7:0] $end
$var wire 8 V out_10 [7:0] $end
$var wire 8 W out_11 [7:0] $end
$var wire 8 X out_12 [7:0] $end
$var wire 8 Y out_13 [7:0] $end
$var wire 8 Z out_14 [7:0] $end
$var wire 8 [ out_15 [7:0] $end
$var wire 8 \ out_16 [7:0] $end
$var wire 8 ] out_2 [7:0] $end
$var wire 8 ^ out_3 [7:0] $end
$var wire 8 _ out_4 [7:0] $end
$var wire 8 ` out_5 [7:0] $end
$var wire 8 a out_6 [7:0] $end
$var wire 8 b out_7 [7:0] $end
$var wire 8 c out_8 [7:0] $end
$var wire 8 d out_9 [7:0] $end
$var wire 1 C rst $end
$var wire 1 D start $end
$var parameter 2 e DONE $end
$var parameter 2 f IDLE $end
$var parameter 2 g LOAD $end
$var parameter 2 h SORTER $end
$var reg 1 1 done $end
$var reg 2 i iter_counter [1:0] $end
$var reg 2 j state [1:0] $end
$scope module c0 $end
$var wire 8 k out0 [7:0] $end
$var wire 8 l out1 [7:0] $end
$var wire 8 m out2 [7:0] $end
$var wire 8 n out3 [7:0] $end
$var wire 8 o s2_0 [7:0] $end
$var wire 8 p s2_3 [7:0] $end
$var wire 8 q s_3 [7:0] $end
$var wire 8 r s_2 [7:0] $end
$var wire 8 s s_1 [7:0] $end
$var wire 8 t s_0 [7:0] $end
$var wire 8 u s2_2 [7:0] $end
$var wire 8 v s2_1 [7:0] $end
$var wire 8 w s1_3 [7:0] $end
$var wire 8 x s1_2 [7:0] $end
$var wire 8 y s1_1 [7:0] $end
$var wire 8 z s1_0 [7:0] $end
$var wire 8 { in_3 [7:0] $end
$var wire 8 | in_2 [7:0] $end
$var wire 8 } in_1 [7:0] $end
$var wire 8 ~ in_0 [7:0] $end
$upscope $end
$scope module c1 $end
$var wire 8 !" out0 [7:0] $end
$var wire 8 "" out1 [7:0] $end
$var wire 8 #" out2 [7:0] $end
$var wire 8 $" out3 [7:0] $end
$var wire 8 %" s2_0 [7:0] $end
$var wire 8 &" s2_3 [7:0] $end
$var wire 8 '" s_3 [7:0] $end
$var wire 8 (" s_2 [7:0] $end
$var wire 8 )" s_1 [7:0] $end
$var wire 8 *" s_0 [7:0] $end
$var wire 8 +" s2_2 [7:0] $end
$var wire 8 ," s2_1 [7:0] $end
$var wire 8 -" s1_3 [7:0] $end
$var wire 8 ." s1_2 [7:0] $end
$var wire 8 /" s1_1 [7:0] $end
$var wire 8 0" s1_0 [7:0] $end
$var wire 8 1" in_3 [7:0] $end
$var wire 8 2" in_2 [7:0] $end
$var wire 8 3" in_1 [7:0] $end
$var wire 8 4" in_0 [7:0] $end
$upscope $end
$scope module c2 $end
$var wire 8 5" out0 [7:0] $end
$var wire 8 6" out1 [7:0] $end
$var wire 8 7" out2 [7:0] $end
$var wire 8 8" out3 [7:0] $end
$var wire 8 9" s2_0 [7:0] $end
$var wire 8 :" s2_3 [7:0] $end
$var wire 8 ;" s_3 [7:0] $end
$var wire 8 <" s_2 [7:0] $end
$var wire 8 =" s_1 [7:0] $end
$var wire 8 >" s_0 [7:0] $end
$var wire 8 ?" s2_2 [7:0] $end
$var wire 8 @" s2_1 [7:0] $end
$var wire 8 A" s1_3 [7:0] $end
$var wire 8 B" s1_2 [7:0] $end
$var wire 8 C" s1_1 [7:0] $end
$var wire 8 D" s1_0 [7:0] $end
$var wire 8 E" in_3 [7:0] $end
$var wire 8 F" in_2 [7:0] $end
$var wire 8 G" in_1 [7:0] $end
$var wire 8 H" in_0 [7:0] $end
$upscope $end
$scope module c3 $end
$var wire 8 I" out0 [7:0] $end
$var wire 8 J" out1 [7:0] $end
$var wire 8 K" out2 [7:0] $end
$var wire 8 L" out3 [7:0] $end
$var wire 8 M" s2_0 [7:0] $end
$var wire 8 N" s2_3 [7:0] $end
$var wire 8 O" s_3 [7:0] $end
$var wire 8 P" s_2 [7:0] $end
$var wire 8 Q" s_1 [7:0] $end
$var wire 8 R" s_0 [7:0] $end
$var wire 8 S" s2_2 [7:0] $end
$var wire 8 T" s2_1 [7:0] $end
$var wire 8 U" s1_3 [7:0] $end
$var wire 8 V" s1_2 [7:0] $end
$var wire 8 W" s1_1 [7:0] $end
$var wire 8 X" s1_0 [7:0] $end
$var wire 8 Y" in_3 [7:0] $end
$var wire 8 Z" in_2 [7:0] $end
$var wire 8 [" in_1 [7:0] $end
$var wire 8 \" in_0 [7:0] $end
$upscope $end
$scope module r0 $end
$var wire 8 ]" in_0 [7:0] $end
$var wire 8 ^" in_1 [7:0] $end
$var wire 8 _" in_2 [7:0] $end
$var wire 8 `" in_3 [7:0] $end
$var wire 8 a" out0 [7:0] $end
$var wire 8 b" out1 [7:0] $end
$var wire 8 c" out2 [7:0] $end
$var wire 8 d" out3 [7:0] $end
$var wire 8 e" s2_0 [7:0] $end
$var wire 8 f" s2_3 [7:0] $end
$var wire 8 g" s_3 [7:0] $end
$var wire 8 h" s_2 [7:0] $end
$var wire 8 i" s_1 [7:0] $end
$var wire 8 j" s_0 [7:0] $end
$var wire 8 k" s2_2 [7:0] $end
$var wire 8 l" s2_1 [7:0] $end
$var wire 8 m" s1_3 [7:0] $end
$var wire 8 n" s1_2 [7:0] $end
$var wire 8 o" s1_1 [7:0] $end
$var wire 8 p" s1_0 [7:0] $end
$upscope $end
$scope module r1 $end
$var wire 8 q" in_0 [7:0] $end
$var wire 8 r" in_1 [7:0] $end
$var wire 8 s" in_2 [7:0] $end
$var wire 8 t" in_3 [7:0] $end
$var wire 8 u" out0 [7:0] $end
$var wire 8 v" out1 [7:0] $end
$var wire 8 w" out2 [7:0] $end
$var wire 8 x" out3 [7:0] $end
$var wire 8 y" s2_0 [7:0] $end
$var wire 8 z" s2_3 [7:0] $end
$var wire 8 {" s_3 [7:0] $end
$var wire 8 |" s_2 [7:0] $end
$var wire 8 }" s_1 [7:0] $end
$var wire 8 ~" s_0 [7:0] $end
$var wire 8 !# s2_2 [7:0] $end
$var wire 8 "# s2_1 [7:0] $end
$var wire 8 ## s1_3 [7:0] $end
$var wire 8 $# s1_2 [7:0] $end
$var wire 8 %# s1_1 [7:0] $end
$var wire 8 &# s1_0 [7:0] $end
$upscope $end
$scope module r2 $end
$var wire 8 '# in_0 [7:0] $end
$var wire 8 (# in_1 [7:0] $end
$var wire 8 )# in_2 [7:0] $end
$var wire 8 *# in_3 [7:0] $end
$var wire 8 +# out0 [7:0] $end
$var wire 8 ,# out1 [7:0] $end
$var wire 8 -# out2 [7:0] $end
$var wire 8 .# out3 [7:0] $end
$var wire 8 /# s2_0 [7:0] $end
$var wire 8 0# s2_3 [7:0] $end
$var wire 8 1# s_3 [7:0] $end
$var wire 8 2# s_2 [7:0] $end
$var wire 8 3# s_1 [7:0] $end
$var wire 8 4# s_0 [7:0] $end
$var wire 8 5# s2_2 [7:0] $end
$var wire 8 6# s2_1 [7:0] $end
$var wire 8 7# s1_3 [7:0] $end
$var wire 8 8# s1_2 [7:0] $end
$var wire 8 9# s1_1 [7:0] $end
$var wire 8 :# s1_0 [7:0] $end
$upscope $end
$scope module r3 $end
$var wire 8 ;# in_0 [7:0] $end
$var wire 8 <# in_1 [7:0] $end
$var wire 8 =# in_2 [7:0] $end
$var wire 8 ># in_3 [7:0] $end
$var wire 8 ?# out0 [7:0] $end
$var wire 8 @# out1 [7:0] $end
$var wire 8 A# out2 [7:0] $end
$var wire 8 B# out3 [7:0] $end
$var wire 8 C# s2_0 [7:0] $end
$var wire 8 D# s2_3 [7:0] $end
$var wire 8 E# s_3 [7:0] $end
$var wire 8 F# s_2 [7:0] $end
$var wire 8 G# s_1 [7:0] $end
$var wire 8 H# s_0 [7:0] $end
$var wire 8 I# s2_2 [7:0] $end
$var wire 8 J# s2_1 [7:0] $end
$var wire 8 K# s1_3 [7:0] $end
$var wire 8 L# s1_2 [7:0] $end
$var wire 8 M# s1_1 [7:0] $end
$var wire 8 N# s1_0 [7:0] $end
$upscope $end
$upscope $end
$upscope $end
$enddefinitions $end
$comment Show the parameter values. $end
$dumpall
b10 h
b1 g
b0 f
b11 e
$end
#0
$dumpvars
bx N#
bx M#
bx L#
bx K#
bx J#
bx I#
bx H#
bx G#
bx F#
bx E#
bx D#
bx C#
bx B#
bx A#
bx @#
bx ?#
bx >#
bx =#
bx <#
bx ;#
bx :#
bx 9#
bx 8#
bx 7#
bx 6#
bx 5#
bx 4#
bx 3#
bx 2#
bx 1#
bx 0#
bx /#
bx .#
bx -#
bx ,#
bx +#
bx *#
bx )#
bx (#
bx '#
bx &#
bx %#
bx $#
bx ##
bx "#
bx !#
bx ~"
bx }"
bx |"
bx {"
bx z"
bx y"
bx x"
bx w"
bx v"
bx u"
bx t"
bx s"
bx r"
bx q"
bx p"
bx o"
bx n"
bx m"
bx l"
bx k"
bx j"
bx i"
bx h"
bx g"
bx f"
bx e"
bx d"
bx c"
bx b"
bx a"
bx `"
bx _"
bx ^"
bx ]"
bx \"
bx ["
bx Z"
bx Y"
bx X"
bx W"
bx V"
bx U"
bx T"
bx S"
bx R"
bx Q"
bx P"
bx O"
bx N"
bx M"
bx L"
bx K"
bx J"
bx I"
bx H"
bx G"
bx F"
bx E"
bx D"
bx C"
bx B"
bx A"
bx @"
bx ?"
bx >"
bx ="
bx <"
bx ;"
bx :"
bx 9"
bx 8"
bx 7"
bx 6"
bx 5"
bx 4"
bx 3"
bx 2"
bx 1"
bx 0"
bx /"
bx ."
bx -"
bx ,"
bx +"
bx *"
bx )"
bx ("
bx '"
bx &"
bx %"
bx $"
bx #"
bx ""
bx !"
bx ~
bx }
bx |
bx {
bx z
bx y
bx x
bx w
bx v
bx u
bx t
bx s
bx r
bx q
bx p
bx o
bx n
bx m
bx l
bx k
b0 j
b0 i
bx d
bx c
bx b
bx a
bx `
bx _
bx ^
bx ]
bx \
bx [
bx Z
bx Y
bx X
bx W
bx V
bx U
b11001000 T
b1011010 S
b1111000 R
b1100100 Q
b10010110 P
b101 O
b11110 N
b1010000 M
b11100110 L
b11111010 K
b11110000 J
b11111111 I
b10100000 H
b11011100 G
b10110100 F
b1010 E
0D
1C
b11001000 B
b1011010 A
b1111000 @
b1100100 ?
b10010110 >
b101 =
b11110 <
b1010000 ;
b11100110 :
b11111010 9
b11110000 8
b11111111 7
b10100000 6
b11011100 5
b10110100 4
b1010 3
02
01
bx 0
bx /
bx .
bx -
bx ,
bx +
bx *
bx )
bx (
bx '
bx &
bx %
bx $
bx #
bx "
bx !
$end
#5000
12
#10000
02
#15000
12
#20000
02
0C
#25000
b1 j
1D
12
#30000
02
#35000
b1111000 ""
b1111000 ,"
b10110100 #"
b10110100 +"
b1100100 6"
b1100100 @"
b11001000 7"
b11001000 ?"
b10010110 l
b10010110 v
b10100000 m
b10100000 u
b1111000 ."
b11111010 $"
b11111010 &"
b11111010 -"
b1010 !"
b1010 %"
b1010 0"
b10110100 /"
b1100100 B"
b11110000 8"
b11110000 :"
b11110000 A"
b11110 5"
b11110 9"
b11110 D"
b11001000 C"
b1011010 J"
b1011010 T"
b11011100 K"
b11011100 S"
b11111010 '"
b10110100 ("
b11110000 ;"
b11001000 <"
b10010110 x
b11111111 n
b11111111 p
b11111111 w
b101 k
b101 o
b101 z
b10100000 y
b1111000 )"
b1010 *"
b1100100 ="
b11110 >"
b1011010 V"
b11100110 L"
b11100110 N"
b11100110 U"
b1010000 I"
b1010000 M"
b1010000 X"
b11011100 W"
b11110000 E"
b11110000 @#
b11110000 J#
b11111010 1"
b11111010 A#
b11111010 I#
b11111111 q
b10100000 r
b10110100 2"
b10110100 ,#
b10110100 6#
b11001000 F"
b11001000 -#
b11001000 5#
b11100110 O"
b11011100 P"
b1100100 G"
b1100100 v"
b1100100 "#
b1111000 3"
b1111000 w"
b1111000 !#
b10010110 s
b101 t
b1010 4"
b1010 b"
b1010 l"
b11110 H"
b11110 c"
b11110 k"
b1011010 Q"
b1010000 R"
b11100110 Y"
b11100110 ?#
b11100110 C#
b11100110 N#
b11110000 M#
b11111010 L#
b11111111 {
b11111111 B#
b11111111 D#
b11111111 K#
b10100000 |
b10100000 +#
b10100000 /#
b10100000 :#
b10110100 9#
b11001000 8#
b11011100 Z"
b11011100 .#
b11011100 0#
b11011100 7#
b1011010 ["
b1011010 u"
b1011010 y"
b1011010 &#
b1100100 %#
b1111000 $#
b10010110 }
b10010110 x"
b10010110 z"
b10010110 ##
b101 ~
b101 a"
b101 e"
b101 p"
b1010 o"
b11110 n"
b1010000 \"
b1010000 d"
b1010000 f"
b1010000 m"
b11100110 F#
b11111010 E#
b11110000 H#
b11111111 G#
b10100000 2#
b11011100 1#
b10110100 4#
b11001000 3#
b1011010 |"
b1111000 {"
b1100100 ~"
b10010110 }"
b101 h"
b11110 g"
b1010 j"
b1010000 i"
b10 j
b11100110 )
b11100110 \
b11100110 >#
b11111010 *
b11111010 [
b11111010 =#
b11110000 +
b11110000 Z
b11110000 <#
b11111111 ,
b11111111 Y
b11111111 ;#
b10100000 -
b10100000 X
b10100000 *#
b11011100 .
b11011100 W
b11011100 )#
b10110100 /
b10110100 V
b10110100 (#
b11001000 !
b11001000 d
b11001000 '#
b1011010 "
b1011010 c
b1011010 t"
b1111000 #
b1111000 b
b1111000 s"
b1100100 $
b1100100 a
b1100100 r"
b10010110 %
b10010110 `
b10010110 q"
b101 &
b101 _
b101 `"
b11110 '
b11110 ^
b11110 _"
b1010000 (
b1010000 ]
b1010000 ^"
b1010 0
b1010 U
b1010 ]"
0D
12
#40000
02
#45000
b11110000 L#
b11111010 M#
b11001000 9#
b10110100 8#
b1100100 $#
b1111000 %#
b1010 n"
b11110 o"
b11110000 E#
b11111010 H#
b11001000 2#
b10100000 4#
b10110100 3#
b1100100 {"
b1111000 ~"
b11110 h"
b1010000 g"
b1010 i"
b101 j"
b1 i
b11110000 *
b11110000 [
b11110000 =#
b11111010 +
b11111010 Z
b11111010 <#
b11011100 -
b11011100 X
b11011100 *#
b11001000 .
b11001000 W
b11001000 )#
b10100000 !
b10100000 d
b10100000 '#
b1100100 #
b1100100 b
b1100100 s"
b1111000 $
b1111000 a
b1111000 r"
b1010000 &
b1010000 _
b1010000 `"
b1010 (
b1010 ]
b1010 ^"
b101 0
b101 U
b101 ]"
12
#50000
02
#55000
b10 i
12
#60000
02
#65000
b11 j
12
#70000
02
#75000
b0 j
11
12
